.pre-commit-config.yaml
cylindra-1.0.2.dist-info/METADATA
cylindra-1.0.2.dist-info/WHEEL
cylindra-1.0.2.dist-info/entry_points.txt
cylindra-1.0.2.dist-info/licenses/LICENSE
cylindra/__init__.py
cylindra/__main__.py
cylindra/_config.py
cylindra/_cylindra_ext.pyi
cylindra/_cylindra_ext.pypy311-pp73-x86_64-linux-gnu.so
cylindra/_dask.py
cylindra/_data/BtubAB.json
cylindra/_data/TMV.json
cylindra/_data/actin.json
cylindra/_data/eukaryotic_MT.json
cylindra/_napari/__init__.py
cylindra/_napari/_layer_controls.py
cylindra/_napari/_layers.py
cylindra/_napari/_sub_controls.py
cylindra/_previews.py
cylindra/_shared_doc.py
cylindra/annotations.py
cylindra/cli/__init__.py
cylindra/cli/_base.py
cylindra/cli/_cookiecutter_template/cookiecutter.json
cylindra/cli/_cookiecutter_template/hooks/post_gen_project.py
cylindra/cli/_cookiecutter_template/{{cookiecutter.plugin_name}}/.gitignore
cylindra/cli/_cookiecutter_template/{{cookiecutter.plugin_name}}/LICENSE
cylindra/cli/_cookiecutter_template/{{cookiecutter.plugin_name}}/README.md
cylindra/cli/_cookiecutter_template/{{cookiecutter.plugin_name}}/licenses/Apache-2.txt
cylindra/cli/_cookiecutter_template/{{cookiecutter.plugin_name}}/licenses/BSD-3.txt
cylindra/cli/_cookiecutter_template/{{cookiecutter.plugin_name}}/licenses/GPL-3.txt
cylindra/cli/_cookiecutter_template/{{cookiecutter.plugin_name}}/licenses/MIT.txt
cylindra/cli/_cookiecutter_template/{{cookiecutter.plugin_name}}/pyproject.toml
cylindra/cli/_cookiecutter_template/{{cookiecutter.plugin_name}}/tests/__init__.py
cylindra/cli/_cookiecutter_template/{{cookiecutter.plugin_name}}/{{cookiecutter.module_name}}/__init__.py
cylindra/cli/_cookiecutter_template/{{cookiecutter.plugin_name}}/{{cookiecutter.module_name}}/core.py
cylindra/cli/average.py
cylindra/cli/config.py
cylindra/cli/find.py
cylindra/cli/new.py
cylindra/cli/none.py
cylindra/cli/open.py
cylindra/cli/plugin.py
cylindra/cli/preview.py
cylindra/cli/run.py
cylindra/cli/workflow.py
cylindra/components/__init__.py
cylindra/components/_base.py
cylindra/components/_cylinder_params.py
cylindra/components/_ftprops.py
cylindra/components/_peak.py
cylindra-1.0.2.dist-info/RECORD
