Metadata-Version: 2.4
Name: cylindra
Version: 1.0.2
Classifier: Programming Language :: Rust
Classifier: Programming Language :: Python :: Implementation :: CPython
Classifier: Programming Language :: Python :: Implementation :: PyPy
Classifier: Programming Language :: Python :: 3 :: Only
Classifier: Programming Language :: Python :: 3.11
Classifier: Programming Language :: Python :: 3.12
Classifier: Programming Language :: Python :: 3.13
Classifier: Programming Language :: Python :: 3.14
Classifier: Framework :: napari
Requires-Dist: impy-array>=2.4.10
Requires-Dist: acryo>=0.5.1
Requires-Dist: macro-kit>=0.4.6
Requires-Dist: magicgui>=0.8.1
Requires-Dist: magic-class>=0.7.20
Requires-Dist: psygnal>=0.9.1
Requires-Dist: superqt[iconify]>=0.6.1
Requires-Dist: pydantic>=2.8.2
Requires-Dist: pyqtgraph>=0.12.4
Requires-Dist: pyarrow>=11.0.0
Requires-Dist: numpy>=1.23.0
Requires-Dist: scipy>=1.11.3
Requires-Dist: pandas>=1.5.0
Requires-Dist: polars>=1.19.0
Requires-Dist: scikit-image>=0.21.0
Requires-Dist: napari>=0.6.5
Requires-Dist: qtpy>=2.3.1
Requires-Dist: qt-command-palette>=0.0.7
Requires-Dist: matplotlib>=3.8.1
Requires-Dist: rich>=13.6.0
Requires-Dist: dask>=2023.12.1,<2025.0.0
Requires-Dist: platformdirs>=4.3.6
Requires-Dist: pytest ; extra == 'testing'
Requires-Dist: pytest-qt ; extra == 'testing'
Requires-Dist: pytest-cov ; extra == 'testing'
Requires-Dist: pyqt6 ; extra == 'testing'
Requires-Dist: scikit-learn>=1.2.2 ; extra == 'testing'
Requires-Dist: mrcfile>=1.3.0 ; extra == 'testing'
Requires-Dist: tifffile>=2023.2.28 ; extra == 'testing'
Requires-Dist: starfile>=0.5.11 ; extra == 'testing'
Requires-Dist: imodmodel>=0.1.0 ; extra == 'testing'
Requires-Dist: cookiecutter ; extra == 'testing'
Requires-Dist: maturin>=1.9.6,<2.0.0 ; extra == 'testing'
Requires-Dist: pyqt6 ; extra == 'all'
Requires-Dist: scikit-learn>=1.2.2 ; extra == 'all'
Requires-Dist: mrcfile>=1.3.0 ; extra == 'all'
Requires-Dist: tifffile>=2023.2.28 ; extra == 'all'
Requires-Dist: starfile ; extra == 'all'
Requires-Dist: imodmodel ; extra == 'all'
Requires-Dist: cookiecutter ; extra == 'all'
Requires-Dist: pyqt6 ; extra == 'docs'
Requires-Dist: mrcfile>=1.3.0 ; extra == 'docs'
Requires-Dist: mkdocs>=1.6.1 ; extra == 'docs'
Requires-Dist: mkdocs-autorefs>=1.4.2 ; extra == 'docs'
Requires-Dist: mkdocs-gen-files>=0.5.0 ; extra == 'docs'
Requires-Dist: mkdocs-material>=9.6.15 ; extra == 'docs'
Requires-Dist: mkdocs-material-extensions>=1.3.1 ; extra == 'docs'
Requires-Dist: mkdocstrings>=0.29.1 ; extra == 'docs'
Requires-Dist: mkdocstrings-python>=1.16.12 ; extra == 'docs'
Requires-Dist: maturin>=1.5.0,<2.0.0 ; extra == 'docs'
Provides-Extra: testing
Provides-Extra: all
Provides-Extra: docs
License-File: LICENSE
Summary: Spectral analysis, simulation and subtomogram averaging of heterogenic cylindrical structures
Keywords: gui,napari,cryo-ET,tomography
Author: Hanjin Liu
Author-email: liuhanjin.sc@gmail.com
Requires-Python: >=3.11
